LICENSE
README.md
setup.py
Flask_Middlewares.egg-info/PKG-INFO
Flask_Middlewares.egg-info/SOURCES.txt
Flask_Middlewares.egg-info/dependency_links.txt
Flask_Middlewares.egg-info/requires.txt
Flask_Middlewares.egg-info/top_level.txt
flask_middlewares/__init__.py
flask_middlewares/core.py
flask_middlewares/errors.py
flask_middlewares/registrars.py
flask_middlewares/tools.py