Metadata-Version: 2.1
Name: Flask-Middlewares
Version: 2.0.0
Summary: Middlware library for your Flask application
Home-page: https://github.com/TheArtur128/Flask-middlewares
Download-URL: https://github.com/TheArtur128/Flask-middlewares/archive/refs/tags/v2.0.0.zip
Author: Arthur
Author-email: s9339307190@gmail.com
License: GNU General Public License v3.0
Keywords: flask,middleware,library,middlewares
Classifier: Programming Language :: Python :: 3.11
Requires-Python: >=3.11
License-File: LICENSE
